{"dossierParlementaire": {"@xmlns": "http://schemas.assemblee-nationale.fr/referentiel", "@xmlns:xsi": "http://www.w3.org/2001/XMLSchema-instance", "@xsi:type": "DossierLegislatif_Type", "uid": "DLR5L17N51499", "legislature": "17", "titreDossier": {"titre": "Reconnaissance de la Nation envers les rapatri\u00e9s d\u2019Indochine et r\u00e9paration des pr\u00e9judices subis par ceux-ci et leurs familles du fait de l'indignit\u00e9 de leurs conditions d'accueil et de vie dans certaines structures sur le territoire fran\u00e7ais", "titreChemin": "reconnaissance_nation_rapatries_indochine_17", "senatChemin": "http://www.senat.fr/dossier-legislatif/ppl24-685.html"}, "procedureParlementaire": {"code": "2", "libelle": "Proposition de loi ordinaire"}, "initiateur": {"acteurs": {"acteur": {"acteurRef": "PA609332", "mandatRef": "PM840396"}}}, "actesLegislatifs": {"acteLegislatif": [{"@xsi:type": "Etape_Type", "uid": "L17-AN1-51499", "codeActe": "AN1", "libelleActe": {"nomCanonique": "1\u00e8re lecture (1\u00e8re assembl\u00e9e saisie)", "libelleCourt": "1\u00e8re lecture"}, "organeRef": "PO838901", "dateActe": null, "actesLegislatifs": {"acteLegislatif": [{"@xsi:type": "DepotInitiative_Type", "uid": "L17-VD223832DI", "codeActe": "AN1-DEPOT", "libelleActe": {"nomCanonique": "1er d\u00e9p\u00f4t d'une initiative.", "libelleCourt": "1er d\u00e9p\u00f4t d'une initiative."}, "organeRef": "PO838901", "dateActe": "2025-02-13T00:00:00.000+01:00", "actesLegislatifs": null, "texteAssocie": "PIONANR5L17B0949"}, {"@xsi:type": "Etape_Type", "uid": "L17-AN1-COM-51499", "codeActe": "AN1-COM", "libelleActe": {"nomCanonique": "Travaux des commissions", "libelleCourt": "Travaux des commissions"}, "organeRef": "PO838901", "dateActe": null, "actesLegislatifs": {"acteLegislatif": {"@xsi:type": "Etape_Type", "uid": "L17-VD223833CF", "codeActe": "AN1-COM-FOND", "libelleActe": {"nomCanonique": "Travaux de la commission saisie au fond", "libelleCourt": "Travaux de la commission saisie au fond"}, "organeRef": "PO59046", "dateActe": null, "actesLegislatifs": {"acteLegislatif": [{"@xsi:type": "SaisieComFond_Type", "uid": "L17-VD223833CFS", "codeActe": "AN1-COM-FOND-SAISIE", "libelleActe": {"nomCanonique": "Renvoi en commission au fond", "libelleCourt": "Renvoi en commission au fond"}, "organeRef": "PO59046", "dateActe": "2025-02-13T00:00:00.000+01:00", "actesLegislatifs": null}, {"@xsi:type": "NominRapporteurs_Type", "uid": "L17-VD225967", "codeActe": "AN1-COM-FOND-NOMIN", "libelleActe": {"nomCanonique": "Nomination de rapporteur", "libelleCourt": "Nomination de rapporteur"}, "organeRef": "PO59046", "dateActe": "2025-05-21T00:00:00.000+02:00", "actesLegislatifs": null, "rapporteurs": {"rapporteur": {"acteurRef": "PA609332", "typeRapporteur": "rapporteur"}}, "reunion": null}, {"@xsi:type": "DiscussionCommission_Type", "uid": "L17-VD225879R35725", "codeActe": "AN1-COM-FOND-REUNION", "libelleActe": {"nomCanonique": "R\u00e9union de commission", "libelleCourt": "R\u00e9union de commission"}, "organeRef": "PO59046", "dateActe": "2025-05-21T11:15:00.000+02:00", "actesLegislatifs": null, "reunionRef": "RUANR5L17S2025IDC455987", "odjRef": "RUANR5L17S2025IDC455987PT35725"}, {"@xsi:type": "DiscussionCommission_Type", "uid": "L17-VD225879R35727", "codeActe": "AN1-COM-FOND-REUNION", "libelleActe": {"nomCanonique": "R\u00e9union de commission", "libelleCourt": "R\u00e9union de commission"}, "organeRef": "PO59046", "dateActe": "2025-05-28T11:05:00.000+02:00", "actesLegislatifs": null, "reunionRef": "RUANR5L17S2025IDC456403", "odjRef": "RUANR5L17S2025IDC456403PT35727"}, {"@xsi:type": "DiscussionCommission_Type", "uid": "L17-VD225879R35782", "codeActe": "AN1-COM-FOND-REUNION", "libelleActe": {"nomCanonique": "R\u00e9union de commission", "libelleCourt": "R\u00e9union de commission"}, "organeRef": "PO59046", "dateActe": "2025-06-03T14:00:00.000+02:00", "actesLegislatifs": null, "reunionRef": "RUANR5L17S2025IDC456649", "odjRef": "RUANR5L17S2025IDC456649PT35782"}, {"@xsi:type": "DepotRapport_Type", "uid": "L17-VD226115", "codeActe": "AN1-COM-FOND-RAPPORT", "libelleActe": {"nomCanonique": "D\u00e9p\u00f4t de rapport", "libelleCourt": "D\u00e9p\u00f4t de rapport"}, "organeRef": "PO59046", "dateActe": "2025-05-28T00:00:00.000+02:00", "actesLegislatifs": null, "texteAssocie": "RAPPANR5L17B1474", "texteAdopte": "PIONANR5L17BTC1474"}]}}}}, {"@xsi:type": "Etape_Type", "uid": "L17-AN1-DEBATS-51499", "codeActe": "AN1-DEBATS", "libelleActe": {"nomCanonique": "Discussion en s\u00e9ance publique", "libelleCourt": "Discussion en s\u00e9ance publique"}, "organeRef": "PO838901", "dateActe": null, "actesLegislatifs": {"acteLegislatif": [{"@xsi:type": "DiscussionSeancePublique_Type", "uid": "L17-VD225684S50220", "codeActe": "AN1-DEBATS-SEANCE", "libelleActe": {"nomCanonique": "Discussion en s\u00e9ance publique", "libelleCourt": "Discussion en s\u00e9ance publique"}, "organeRef": "PO838901", "dateActe": "2025-06-03T00:00:00.000+02:00", "actesLegislatifs": null, "reunionRef": "RUANR5L17S2025IDS29499", "odjRef": "RUANR5L17S2025IDS29499PT50220"}, {"@xsi:type": "DiscussionSeancePublique_Type", "uid": "L17-VD225684S50225", "codeActe": "AN1-DEBATS-SEANCE", "libelleActe": {"nomCanonique": "Discussion en s\u00e9ance publique", "libelleCourt": "Discussion en s\u00e9ance publique"}, "organeRef": "PO838901", "dateActe": "2025-06-03T00:00:00.000+02:00", "actesLegislatifs": null, "reunionRef": "RUANR5L17S2025IDS29500", "odjRef": "RUANR5L17S2025IDS29500PT50225"}, {"@xsi:type": "Decision_Type", "uid": "L17-VD226249DEC", "codeActe": "AN1-DEBATS-DEC", "libelleActe": {"nomCanonique": "D\u00e9cision", "libelleCourt": "D\u00e9cision"}, "organeRef": "PO838901", "dateActe": "2025-06-03T00:00:00.000+02:00", "actesLegislatifs": null, "statutConclusion": {"fam_code": "TSORTF01", "libelle": "adopt\u00e9e"}, "reunionRef": "RUANR5L17S2025IDS29500", "voteRefs": {"voteRef": "VTANR5L17V2220"}, "textesAssocies": {"texteAssocie": [{"typeTexte": "BTA", "refTexteAssocie": "PIONANR5L17BTA0129"}, {"typeTexte": "TAP", "refTexteAssocie": "PIONANR5L17TAP0129"}]}}]}}]}}, {"@xsi:type": "Etape_Type", "uid": "L17-SN1-51499", "codeActe": "SN1", "libelleActe": {"nomCanonique": "1\u00e8re lecture (2\u00e8me assembl\u00e9e saisie)", "libelleCourt": "1\u00e8re lecture"}, "organeRef": "PO78718", "dateActe": null, "actesLegislatifs": {"acteLegislatif": [{"@xsi:type": "DepotInitiativeNavette_Type", "uid": "L17-VD226337DIN", "codeActe": "SN1-DEPOT", "libelleActe": {"nomCanonique": "D\u00e9p\u00f4t d'une initiative en navette", "libelleCourt": "D\u00e9p\u00f4t d'une initiative en navette"}, "organeRef": "PO78718", "dateActe": "2025-06-04T00:00:00.000+02:00", "actesLegislatifs": null, "texteAssocie": "PIONSNR5S459B0685", "provenance": "PO838901", "depotInitialLectureDefinitiveRef": null}, {"@xsi:type": "Etape_Type", "uid": "L17-SN1-COM-51499", "codeActe": "SN1-COM", "libelleActe": {"nomCanonique": "Travaux des commissions", "libelleCourt": "Travaux des commissions"}, "organeRef": "PO78718", "dateActe": null, "actesLegislatifs": {"acteLegislatif": {"@xsi:type": "Etape_Type", "uid": "L17-VD226338CF", "codeActe": "SN1-COM-FOND", "libelleActe": {"nomCanonique": "Travaux de la commission saisie au fond", "libelleCourt": "Travaux de la commission saisie au fond"}, "organeRef": "PO211493", "dateActe": null, "actesLegislatifs": {"acteLegislatif": {"@xsi:type": "SaisieComFond_Type", "uid": "L17-VD226338CFS", "codeActe": "SN1-COM-FOND-SAISIE", "libelleActe": {"nomCanonique": "Renvoi en commission au fond", "libelleCourt": "Renvoi en commission au fond"}, "organeRef": "PO211493", "dateActe": "2025-06-04T00:00:00.000+02:00", "actesLegislatifs": null}}}}}]}}]}, "fusionDossier": null}}