{"dossierParlementaire": {"@xmlns": "http://schemas.assemblee-nationale.fr/referentiel", "@xmlns:xsi": "http://www.w3.org/2001/XMLSchema-instance", "@xsi:type": "DossierMissionInformation_Type", "uid": "DLR5L17N50203", "legislature": "17", "titreDossier": {"titre": "Mission d'information sur la semaine de quatre jours", "titreChemin": "infomation_semaine_quatre_jours", "senatChemin": null}, "procedureParlementaire": {"code": "10", "libelle": "Mission d'information"}, "initiateur": {"organes": {"organe": {"organeRef": {"uid": "PO846868"}}}}, "actesLegislatifs": {"acteLegislatif": {"@xsi:type": "Etape_Type", "uid": "L17-AN20-50203", "codeActe": "AN20", "libelleActe": {"nomCanonique": "Travaux"}, "organeRef": "PO838901", "dateActe": null, "actesLegislatifs": {"acteLegislatif": {"@xsi:type": "Etape_Type", "uid": "L17-AN20-MISINF-50203", "codeActe": "AN20-MISINF", "libelleActe": {"nomCanonique": "Mission d'information", "libelleCourt": "Mission d'information"}, "organeRef": "PO846868", "dateActe": null, "actesLegislatifs": {"acteLegislatif": {"@xsi:type": "CreationOrganeTemporaire_Type", "uid": "L17-VD220618", "codeActe": "AN20-MISINF-CREA", "libelleActe": {"nomCanonique": "Cr\u00e9ation d'une mission d'information", "libelleCourt": "Cr\u00e9ation d'une mission d'information"}, "organeRef": "PO846868", "dateActe": "2024-07-25T00:00:00.000+02:00", "actesLegislatifs": null, "initiateurs": {"organeRef": "PO846868"}}}}}}}, "fusionDossier": null}}