{"dossierParlementaire": {"@xmlns": "http://schemas.assemblee-nationale.fr/referentiel", "@xmlns:xsi": "http://www.w3.org/2001/XMLSchema-instance", "@xsi:type": "DossierLegislatif_Type", "uid": "DLR5L17N50731", "legislature": "17", "titreDossier": {"titre": "Projet de loi relatif \u00e0 la r\u00e9silience des infrastructures critiques et au renforcement de la cybers\u00e9curit\u00e9", "titreChemin": "DLR5L17N50731", "senatChemin": "http://www.senat.fr/dossier-legislatif/pjl24-033.html"}, "procedureParlementaire": {"code": "1", "libelle": "Projet de loi ordinaire"}, "initiateur": {"acteurs": {"acteur": {"acteurRef": "PA368", "mandatRef": "PM847741"}}}, "actesLegislatifs": {"acteLegislatif": [{"@xsi:type": "Etape_Type", "uid": "L17-SN1-50731", "codeActe": "SN1", "libelleActe": {"nomCanonique": "1\u00e8re lecture (1\u00e8re assembl\u00e9e saisie)", "libelleCourt": "1\u00e8re lecture"}, "organeRef": "PO78718", "dateActe": null, "actesLegislatifs": {"acteLegislatif": [{"@xsi:type": "DepotInitiative_Type", "uid": "L17-VD221709DI", "codeActe": "SN1-DEPOT", "libelleActe": {"nomCanonique": "1er d\u00e9p\u00f4t d'une initiative.", "libelleCourt": "1er d\u00e9p\u00f4t d'une initiative."}, "organeRef": "PO78718", "dateActe": "2024-10-15T00:00:00.000+02:00", "actesLegislatifs": null, "texteAssocie": "PRJLSNR5S459B0033"}, {"@xsi:type": "ProcedureAccelere_Type", "uid": "L17-VD221711", "codeActe": "SN1-PROCACC", "libelleActe": {"nomCanonique": "Le gouvernement d\u00e9clare l'urgence / engage la proc\u00e9dure acc\u00e9l\u00e9r\u00e9e", "libelleCourt": "Le gouvernement d\u00e9clare l'urgence / engage la proc\u00e9dure acc\u00e9l\u00e9r\u00e9e"}, "organeRef": "PO847639", "dateActe": "2024-10-15T00:00:00.000+02:00", "actesLegislatifs": null}, {"@xsi:type": "Etape_Type", "uid": "L17-SN1-COM-50731", "codeActe": "SN1-COM", "libelleActe": {"nomCanonique": "Travaux des commissions", "libelleCourt": "Travaux des commissions"}, "organeRef": "PO78718", "dateActe": null, "actesLegislatifs": {"acteLegislatif": {"@xsi:type": "Etape_Type", "uid": "L17-VD221710CF", "codeActe": "SN1-COM-FOND", "libelleActe": {"nomCanonique": "Travaux de la commission saisie au fond", "libelleCourt": "Travaux de la commission saisie au fond"}, "organeRef": "PO765977", "dateActe": null, "actesLegislatifs": {"acteLegislatif": [{"@xsi:type": "SaisieComFond_Type", "uid": "L17-VD221710CFS", "codeActe": "SN1-COM-FOND-SAISIE", "libelleActe": {"nomCanonique": "Renvoi en commission au fond", "libelleCourt": "Renvoi en commission au fond"}, "organeRef": "PO765977", "dateActe": "2024-10-15T00:00:00.000+02:00", "actesLegislatifs": null}, {"@xsi:type": "NominRapporteurs_Type", "uid": "L17-VD224147", "codeActe": "SN1-COM-FOND-NOMIN", "libelleActe": {"nomCanonique": "Nomination de rapporteur", "libelleCourt": "Nomination de rapporteur"}, "organeRef": "PO765977", "dateActe": null, "actesLegislatifs": null, "rapporteurs": {"rapporteur": [{"acteurRef": "PA703514", "typeRapporteur": "rapporteur"}, {"acteurRef": "PA703513", "typeRapporteur": "rapporteur"}, {"acteurRef": "PA736227", "typeRapporteur": "rapporteur"}]}, "reunion": null}, {"@xsi:type": "DepotRapport_Type", "uid": "L17-VD224150", "codeActe": "SN1-COM-FOND-RAPPORT", "libelleActe": {"nomCanonique": "D\u00e9p\u00f4t de rapport", "libelleCourt": "D\u00e9p\u00f4t de rapport"}, "organeRef": "PO765977", "dateActe": "2025-03-04T00:00:00.000+01:00", "actesLegislatifs": null, "texteAssocie": "RAPPSNR5S459B0393", "texteAdopte": "PRJLSNR5S459BTC0394"}]}}}}, {"@xsi:type": "Etape_Type", "uid": "L17-SN1-DEBATS-50731", "codeActe": "SN1-DEBATS", "libelleActe": {"nomCanonique": "Discussion en s\u00e9ance publique", "libelleCourt": "Discussion en s\u00e9ance publique"}, "organeRef": "PO78718", "dateActe": null, "actesLegislatifs": {"acteLegislatif": [{"@xsi:type": "DiscussionSeancePublique_Type", "uid": "L17-VD224496S49356", "codeActe": "SN1-DEBATS-SEANCE", "libelleActe": {"nomCanonique": "Discussion en s\u00e9ance publique", "libelleCourt": "Discussion en s\u00e9ance publique"}, "organeRef": "PO78718", "dateActe": "2025-03-12T00:00:00.000+01:00", "actesLegislatifs": null, "reunionRef": "RUSNR5L17S2025IDS29277", "odjRef": "RUSNR5L17S2025IDS29277PT49356"}, {"@xsi:type": "Decision_Type", "uid": "L17-VD224497DEC", "codeActe": "SN1-DEBATS-DEC", "libelleActe": {"nomCanonique": "D\u00e9cision", "libelleCourt": "D\u00e9cision"}, "organeRef": "PO78718", "dateActe": "2025-03-12T00:00:00.000+01:00", "actesLegislatifs": null, "statutConclusion": {"fam_code": "TSORTF01", "libelle": "adopt\u00e9"}, "reunionRef": "RUSNR5L17S2025IDS29277", "voteRefs": null, "textesAssocies": {"texteAssocie": {"typeTexte": "BTA", "refTexteAssocie": "PRJLSNR5S459BTA0078"}}}]}}]}}, {"@xsi:type": "Etape_Type", "uid": "L17-AN1-50731", "codeActe": "AN1", "libelleActe": {"nomCanonique": "1\u00e8re lecture (2\u00e8me assembl\u00e9e saisie)", "libelleCourt": "1\u00e8re lecture"}, "organeRef": "PO838901", "dateActe": null, "actesLegislatifs": {"acteLegislatif": [{"@xsi:type": "DepotInitiativeNavette_Type", "uid": "L17-VD224503DIN", "codeActe": "AN1-DEPOT", "libelleActe": {"nomCanonique": "D\u00e9p\u00f4t d'une initiative en navette", "libelleCourt": "D\u00e9p\u00f4t d'une initiative en navette"}, "organeRef": "PO838901", "dateActe": "2025-03-13T00:00:00.000+01:00", "actesLegislatifs": null, "texteAssocie": "PRJLANR5L17B1112", "provenance": "PO78718", "depotInitialLectureDefinitiveRef": null}, {"@xsi:type": "Etape_Type", "uid": "L17-AN1-COM-50731", "codeActe": "AN1-COM", "libelleActe": {"nomCanonique": "Travaux des commissions", "libelleCourt": "Travaux des commissions"}, "organeRef": "PO838901", "dateActe": null, "actesLegislatifs": {"acteLegislatif": {"@xsi:type": "Etape_Type", "uid": "L17-VD224504CF", "codeActe": "AN1-COM-FOND", "libelleActe": {"nomCanonique": "Travaux de la commission saisie au fond", "libelleCourt": "Travaux de la commission saisie au fond"}, "organeRef": "PO866672", "dateActe": null, "actesLegislatifs": {"acteLegislatif": [{"@xsi:type": "SaisieComFond_Type", "uid": "L17-VD224504CFS", "codeActe": "AN1-COM-FOND-SAISIE", "libelleActe": {"nomCanonique": "Renvoi en commission au fond", "libelleCourt": "Renvoi en commission au fond"}, "organeRef": "PO866672", "dateActe": "2025-03-13T00:00:00.000+01:00", "actesLegislatifs": null}, {"@xsi:type": "NominRapporteurs_Type", "uid": "L17-VD227620", "codeActe": "AN1-COM-FOND-NOMIN", "libelleActe": {"nomCanonique": "Nomination de rapporteur", "libelleCourt": "Nomination de rapporteur"}, "organeRef": "PO866672", "dateActe": "2025-04-08T00:00:00.000+02:00", "actesLegislatifs": null, "rapporteurs": {"rapporteur": [{"acteurRef": "PA794094", "typeRapporteur": "rapporteur"}, {"acteurRef": "PA840947", "typeRapporteur": "rapporteur"}, {"acteurRef": "PA794426", "typeRapporteur": "rapporteur"}, {"acteurRef": "PA642695", "typeRapporteur": "rapporteur"}]}, "reunion": null}, {"@xsi:type": "DiscussionCommission_Type", "uid": "L17-VD227613R36097", "codeActe": "AN1-COM-FOND-REUNION", "libelleActe": {"nomCanonique": "R\u00e9union de commission", "libelleCourt": "R\u00e9union de commission"}, "organeRef": "PO866672", "dateActe": "2025-09-09T15:00:00.000+02:00", "actesLegislatifs": null, "reunionRef": "RUANR5L17S2025IDC457346", "odjRef": "RUANR5L17S2025IDC457346PT36097"}, {"@xsi:type": "DiscussionCommission_Type", "uid": "L17-VD227613R36098", "codeActe": "AN1-COM-FOND-REUNION", "libelleActe": {"nomCanonique": "R\u00e9union de commission", "libelleCourt": "R\u00e9union de commission"}, "organeRef": "PO866672", "dateActe": "2025-09-09T16:30:00.000+02:00", "actesLegislatifs": null, "reunionRef": "RUANR5L17S2025IDC457347", "odjRef": "RUANR5L17S2025IDC457347PT36098"}, {"@xsi:type": "DiscussionCommission_Type", "uid": "L17-VD227613R36099", "codeActe": "AN1-COM-FOND-REUNION", "libelleActe": {"nomCanonique": "R\u00e9union de commission", "libelleCourt": "R\u00e9union de commission"}, "organeRef": "PO866672", "dateActe": "2025-09-09T21:30:00.000+02:00", "actesLegislatifs": null, "reunionRef": "RUANR5L17S2025IDC457348", "odjRef": "RUANR5L17S2025IDC457348PT36099"}, {"@xsi:type": "DiscussionCommission_Type", "uid": "L17-VD227613R36100", "codeActe": "AN1-COM-FOND-REUNION", "libelleActe": {"nomCanonique": "R\u00e9union de commission", "libelleCourt": "R\u00e9union de commission"}, "organeRef": "PO866672", "dateActe": "2025-09-10T14:00:00.000+02:00", "actesLegislatifs": null, "reunionRef": "RUANR5L17S2025IDC457349", "odjRef": "RUANR5L17S2025IDC457349PT36100"}, {"@xsi:type": "DepotRapport_Type", "uid": "L17-VD227640", "codeActe": "AN1-COM-FOND-RAPPORT", "libelleActe": {"nomCanonique": "D\u00e9p\u00f4t de rapport", "libelleCourt": "D\u00e9p\u00f4t de rapport"}, "organeRef": "PO866672", "dateActe": "2025-09-10T00:00:00.000+02:00", "actesLegislatifs": null, "texteAssocie": "RAPPANR5L17B1779", "texteAdopte": "PRJLANR5L17BTC1779"}]}}}}]}}]}, "fusionDossier": null}}