{"dossierParlementaire": {"@xmlns": "http://schemas.assemblee-nationale.fr/referentiel", "@xmlns:xsi": "http://www.w3.org/2001/XMLSchema-instance", "@xsi:type": "DossierLegislatif_Type", "uid": "DLR5L17N52086", "legislature": "17", "titreDossier": {"titre": "Subordonner \u00e0 la mise en \u0153uvre d\u2019une consultation des habitants tout projet de cr\u00e9ation de commune nouvelle", "titreChemin": "subordonner_mise_oeuvre_consultation_habitants_projet_creation_commune_nouvelle_17e", "senatChemin": null}, "procedureParlementaire": {"code": "2", "libelle": "Proposition de loi ordinaire"}, "initiateur": {"acteurs": {"acteur": {"acteurRef": "PA842085", "mandatRef": "PM843617"}}}, "actesLegislatifs": {"acteLegislatif": {"@xsi:type": "Etape_Type", "uid": "L17-AN1-52086", "codeActe": "AN1", "libelleActe": {"nomCanonique": "1\u00e8re lecture (1\u00e8re assembl\u00e9e saisie)", "libelleCourt": "1\u00e8re lecture"}, "organeRef": "PO838901", "dateActe": null, "actesLegislatifs": {"acteLegislatif": [{"@xsi:type": "DepotInitiative_Type", "uid": "L17-VD225758DI", "codeActe": "AN1-DEPOT", "libelleActe": {"nomCanonique": "1er d\u00e9p\u00f4t d'une initiative.", "libelleCourt": "1er d\u00e9p\u00f4t d'une initiative."}, "organeRef": "PO838901", "dateActe": "2025-05-13T00:00:00.000+02:00", "actesLegislatifs": null, "texteAssocie": "PIONANR5L17B1414"}, {"@xsi:type": "Etape_Type", "uid": "L17-AN1-COM-52086", "codeActe": "AN1-COM", "libelleActe": {"nomCanonique": "Travaux des commissions", "libelleCourt": "Travaux des commissions"}, "organeRef": "PO838901", "dateActe": null, "actesLegislatifs": {"acteLegislatif": {"@xsi:type": "Etape_Type", "uid": "L17-VD225759CF", "codeActe": "AN1-COM-FOND", "libelleActe": {"nomCanonique": "Travaux de la commission saisie au fond", "libelleCourt": "Travaux de la commission saisie au fond"}, "organeRef": "PO59051", "dateActe": null, "actesLegislatifs": {"acteLegislatif": {"@xsi:type": "SaisieComFond_Type", "uid": "L17-VD225759CFS", "codeActe": "AN1-COM-FOND-SAISIE", "libelleActe": {"nomCanonique": "Renvoi en commission au fond", "libelleCourt": "Renvoi en commission au fond"}, "organeRef": "PO59051", "dateActe": "2025-05-13T00:00:00.000+02:00", "actesLegislatifs": null}}}}}]}}}, "fusionDossier": null}}