{"organe": {"@xmlns": "http://schemas.assemblee-nationale.fr/referentiel", "@xmlns:xsi": "http://www.w3.org/2001/XMLSchema-instance", "@xsi:type": "OrganeParlementaire_Type", "uid": "PO878743", "codeType": "MISINFO", "libelle": "Mission d\u2019information sur l\u2019avenir des commerces de proximit\u00e9", "libelleEdition": "Mission d\u2019information sur l\u2019avenir des commerces de proximit\u00e9", "libelleAbrege": "Avenir des commerces de proximit\u00e9", "libelleAbrev": "COMMERCES", "viMoDe": {"dateDebut": "2026-02-11", "dateAgrement": null, "dateFin": null}, "organeParent": "PO419610", "chambre": null, "regime": "5\u00e8me R\u00e9publique", "legislature": "17", "secretariat": {"secretaire01": null, "secretaire02": null}}}