{"document": {"@xmlns": "http://schemas.assemblee-nationale.fr/referentiel", "@xmlns:xsi": "http://www.w3.org/2001/XMLSchema-instance", "@xsi:type": "texteLoi_Type", "uid": "PIONANR5L17B1733", "legislature": "17", "cycleDeVie": {"chrono": {"dateCreation": "2025-07-11T00:00:00.000+02:00", "dateDepot": "2025-07-11T00:00:00.000+02:00", "datePublication": null, "datePublicationWeb": "2025-07-11T15:15:00.000+02:00"}}, "denominationStructurelle": "Proposition de loi", "provenance": "Texte D\u00e9pos\u00e9", "titres": {"titrePrincipal": "proposition de loi instaurant un versement automatique des allocations de rentr\u00e9e scolaire aux enfants plac\u00e9s \u00e0 leur majorit\u00e9 et instituant un versement de la part des allocations familiales et du revenu de solidarit\u00e9 active concern\u00e9e aux enfants plac\u00e9s \u00e0 leur majorit\u00e9", "titrePrincipalCourt": "Instaurer un versement automatique des allocations de rentr\u00e9e scolaire aux enfants plac\u00e9s \u00e0 leur majorit\u00e9 et instituer un versement de la part des allocations familiales et du revenu de solidarit\u00e9 active concern\u00e9e aux enfants plac\u00e9s \u00e0 leur majorit\u00e9"}, "divisions": null, "dossierRef": "DLR5L17N52525", "redacteur": null, "classification": {"famille": {"depot": {"code": "INITDEP", "libelle": "Initiative en 1er D\u00e9p\u00f4t"}, "classe": {"code": "PIONLOI", "libelle": "Proposition de loi"}}, "type": {"code": "PION", "libelle": "Proposition de loi"}, "sousType": null, "statutAdoption": null}, "auteurs": {"auteur": {"acteur": {"acteurRef": "PA817203", "qualite": "auteur"}}}, "organesReferents": {"organeRef": "PO420120"}, "correction": null, "notice": {"numNotice": "1733", "formule": "instaurant un versement automatique des allocations de rentr\u00e9e scolaire aux enfants plac\u00e9s \u00e0 leur majorit\u00e9 et instituant un versement de la part des allocations familiales et du revenu de solidarit\u00e9 active concern\u00e9e aux enfants plac\u00e9s \u00e0 leur majorit\u00e9", "adoptionConforme": "false"}, "indexation": null, "imprimerie": {"ISSN": null, "ISBN": null, "DIAN": null, "nbPage": null, "prix": null}, "coSignataires": {"coSignataire": [{"acteur": {"acteurRef": "PA722000"}, "dateCosignature": "2025-07-11+02:00", "dateRetraitCosignature": null, "edite": "false"}, {"acteur": {"acteurRef": "PA721750"}, "dateCosignature": "2025-07-11+02:00", "dateRetraitCosignature": null, "edite": "false"}, {"acteur": {"acteurRef": "PA719118"}, "dateCosignature": "2025-07-11+02:00", "dateRetraitCosignature": null, "edite": "false"}, {"acteur": {"acteurRef": "PA794982"}, "dateCosignature": "2025-07-11+02:00", "dateRetraitCosignature": null, "edite": "false"}, {"acteur": {"acteurRef": "PA720154"}, "dateCosignature": "2025-07-11+02:00", "dateRetraitCosignature": null, "edite": "false"}, {"acteur": {"acteurRef": "PA722366"}, "dateCosignature": "2025-07-11+02:00", "dateRetraitCosignature": null, "edite": "false"}, {"acteur": {"acteurRef": "PA719736"}, "dateCosignature": "2025-07-11+02:00", "dateRetraitCosignature": null, "edite": "false"}, {"acteur": {"acteurRef": "PA721296"}, "dateCosignature": "2025-07-11+02:00", "dateRetraitCosignature": null, "edite": "false"}, {"acteur": {"acteurRef": "PA721764"}, "dateCosignature": "2025-07-11+02:00", "dateRetraitCosignature": null, "edite": "false"}, {"acteur": {"acteurRef": "PA841709"}, "dateCosignature": "2025-07-11+02:00", "dateRetraitCosignature": null, "edite": "false"}, {"acteur": {"acteurRef": "PA267200"}, "dateCosignature": "2025-07-11+02:00", "dateRetraitCosignature": null, "edite": "false"}, {"acteur": {"acteurRef": "PA721004"}, "dateCosignature": "2025-07-11+02:00", "dateRetraitCosignature": null, "edite": "false"}, {"acteur": {"acteurRef": "PA720022"}, "dateCosignature": "2025-07-11+02:00", "dateRetraitCosignature": null, "edite": "false"}, {"acteur": {"acteurRef": "PA719412"}, "dateCosignature": "2025-07-11+02:00", "dateRetraitCosignature": null, "edite": "false"}, {"acteur": {"acteurRef": "PA345722"}, "dateCosignature": "2025-07-11+02:00", "dateRetraitCosignature": null, "edite": "false"}, {"acteur": {"acteurRef": "PA719756"}, "dateCosignature": "2025-07-11+02:00", "dateRetraitCosignature": null, "edite": "false"}, {"acteur": {"acteurRef": "PA712014"}, "dateCosignature": "2025-07-11+02:00", "dateRetraitCosignature": null, "edite": "false"}, {"acteur": {"acteurRef": "PA841601"}, "dateCosignature": "2025-07-11+02:00", "dateRetraitCosignature": null, "edite": "false"}, {"acteur": {"acteurRef": "PA720446"}, "dateCosignature": "2025-07-11+02:00", "dateRetraitCosignature": null, "edite": "false"}, {"acteur": {"acteurRef": "PA719080"}, "dateCosignature": "2025-07-11+02:00", "dateRetraitCosignature": null, "edite": "false"}, {"acteur": {"acteurRef": "PA720370"}, "dateCosignature": "2025-07-11+02:00", "dateRetraitCosignature": null, "edite": "false"}, {"acteur": {"acteurRef": "PA795664"}, "dateCosignature": "2025-07-11+02:00", "dateRetraitCosignature": null, "edite": "false"}, {"acteur": {"acteurRef": "PA795962"}, "dateCosignature": "2025-07-11+02:00", "dateRetraitCosignature": null, "edite": "false"}, {"acteur": {"acteurRef": "PA719632"}, "dateCosignature": "2025-07-11+02:00", "dateRetraitCosignature": null, "edite": "false"}, {"acteur": {"acteurRef": "PA721916"}, "dateCosignature": "2025-07-11+02:00", "dateRetraitCosignature": null, "edite": "false"}, {"acteur": {"acteurRef": "PA721426"}, "dateCosignature": "2025-07-11+02:00", "dateRetraitCosignature": null, "edite": "false"}, {"acteur": {"acteurRef": "PA720066"}, "dateCosignature": "2025-07-11+02:00", "dateRetraitCosignature": null, "edite": "false"}, {"acteur": {"acteurRef": "PA795528"}, "dateCosignature": "2025-07-11+02:00", "dateRetraitCosignature": null, "edite": "false"}, {"acteur": {"acteurRef": "PA841927"}, "dateCosignature": "2025-07-11+02:00", "dateRetraitCosignature": null, "edite": "false"}, {"acteur": {"acteurRef": "PA795888"}, "dateCosignature": "2025-07-11+02:00", "dateRetraitCosignature": null, "edite": "false"}, {"acteur": {"acteurRef": "PA793270"}, "dateCosignature": "2025-07-11+02:00", "dateRetraitCosignature": null, "edite": "false"}, {"acteur": {"acteurRef": "PA793416"}, "dateCosignature": "2025-07-11+02:00", "dateRetraitCosignature": null, "edite": "false"}, {"acteur": {"acteurRef": "PA720190"}, "dateCosignature": "2025-07-11+02:00", "dateRetraitCosignature": null, "edite": "false"}, {"acteur": {"acteurRef": "PA794486"}, "dateCosignature": "2025-07-11+02:00", "dateRetraitCosignature": null, "edite": "false"}, {"acteur": {"acteurRef": "PA721584"}, "dateCosignature": "2025-07-11+02:00", "dateRetraitCosignature": null, "edite": "false"}, {"acteur": {"acteurRef": "PA795920"}, "dateCosignature": "2025-07-11+02:00", "dateRetraitCosignature": null, "edite": "false"}, {"acteur": {"acteurRef": "PA722102"}, "dateCosignature": "2025-07-11+02:00", "dateRetraitCosignature": null, "edite": "false"}, {"acteur": {"acteurRef": "PA793194"}, "dateCosignature": "2025-07-11+02:00", "dateRetraitCosignature": null, "edite": "false"}, {"acteur": {"acteurRef": "PA2960"}, "dateCosignature": "2025-07-11+02:00", "dateRetraitCosignature": null, "edite": "false"}, {"acteur": {"acteurRef": "PA795046"}, "dateCosignature": "2025-07-11+02:00", "dateRetraitCosignature": null, "edite": "false"}]}, "depotAmendements": {"amendementsSeance": {"amendable": "false", "dateLimiteDepot": null}, "amendementsCommission": {"commission": {"organeRef": "PO420120", "amendable": "true", "dateLimiteDepot": null}}}}}