{"reunion": {"@xmlns": "http://schemas.assemblee-nationale.fr/referentiel", "@xmlns:xsi": "http://www.w3.org/2001/XMLSchema-instance", "@xsi:type": "reunionCommission_type", "uid": "RUANR5L17S2025IDC454150", "timeStampDebut": "2024-10-24T11:15:00.000+02:00", "timeStampFin": "2024-10-24T12:30:00.000+02:00", "lieu": {"lieuRef": null, "libelleLong": "Visioconf\u00e9rence sans salle"}, "cycleDeVie": {"etat": "Confirm\u00e9", "chrono": {"creation": "2024-12-12T00:00:00.000+01:00", "cloture": null}}, "demandeur": null, "organeReuniRef": "PO847896", "participants": {"participantsInternes": null, "personnesAuditionnees": null}, "visioConference": "true", "sessionRef": null, "ouverturePresse": "false", "captationVideo": "false", "ODJ": {"convocationODJ": {"item": "Table ronde \u00ab Location de courte dur\u00e9e \u00bb \r\u2013 Filpar\rM. Gilles Filippi, pr\u00e9sident\rM. Jean Baptiste Albertini, secr\u00e9taire g\u00e9n\u00e9ral\r\u2013 Loueurs de courte dur\u00e9e (Enterprise, Europcar, Lovauto, Rent a car)\rM. Guirec Grand-Cl\u00e9ment, vice-pr\u00e9sident directeur g\u00e9n\u00e9ral Enterprise Mobility, pr\u00e9sident de la branche \u00ab location de courte dur\u00e9e \u00bb de Mobilians\rMme Aur\u00e9lia Debru, directrice \u00ab Affaires Publiques Enterprise Mobility \u00bb, pr\u00e9sidente de la commission \u00ab affaires publiques \u00bb de la branche \u00ab location de courte dur\u00e9e \u00bb \rM. Nam Nguyen, directeur \u00ab Achat et Revente de v\u00e9hicules \u00bb d\u2019Europcar Mobility Group\rM. Christophe Silvin, directeur g\u00e9n\u00e9ral ex\u00e9cutif de Lovauto\rM. Romain Lecorvaisier, secr\u00e9taire g\u00e9n\u00e9ral de Rent A Car\r\u2013 Mobilians \rMme Doroth\u00e9e Dayraut-Jullian, directrice \u00ab Affaires publiques et communication \u00bb \rM. Tristan Ganivet, charg\u00e9 du m\u00e9tier \u00ab Location courte dur\u00e9e \u00bb"}, "resumeODJ": {"item": "Table ronde \u00ab Location de courte dur\u00e9e \u00bb \r\u2013 Filpar\rM. Gilles Filippi, pr\u00e9sident\rM. Jean Baptiste Albertini, secr\u00e9taire g\u00e9n\u00e9ral\r\u2013 Loueurs de courte dur\u00e9e (Enterprise, Europcar, Lovauto, Rent a car)\rM. Guirec Grand-Cl\u00e9ment, vice-pr\u00e9sident directeur g\u00e9n\u00e9ral Enterprise Mobility, pr\u00e9sident de la branche \u00ab location de courte dur\u00e9e \u00bb de Mobilians\rMme Aur\u00e9lia Debru, directrice \u00ab Affaires Publiques Enterprise Mobility \u00bb, pr\u00e9sidente de la commission \u00ab affaires publiques \u00bb de la branche \u00ab location de courte dur\u00e9e \u00bb \rM. Nam Nguyen, directeur \u00ab Achat et Revente de v\u00e9hicules \u00bb d\u2019Europcar Mobility Group\rM. Christophe Silvin, directeur g\u00e9n\u00e9ral ex\u00e9cutif de Lovauto\rM. Romain Lecorvaisier, secr\u00e9taire g\u00e9n\u00e9ral de Rent A Car\r\u2013 Mobilians \rMme Doroth\u00e9e Dayraut-Jullian, directrice \u00ab Affaires publiques et communication \u00bb \rM. Tristan Ganivet, charg\u00e9 du m\u00e9tier \u00ab Location courte dur\u00e9e \u00bb"}, "pointsODJ": null}, "compteRenduRef": null, "formatReunion": "Ordinaire", "infosReunionsInternationale": {"estReunionInternationale": "false", "listePays": null}}}