{"reunion": {"@xmlns": "http://schemas.assemblee-nationale.fr/referentiel", "@xmlns:xsi": "http://www.w3.org/2001/XMLSchema-instance", "@xsi:type": "seance_type", "uid": "RUANR5L17S2026IDS30110", "timeStampDebut": "2025-12-23T15:00:00.000+01:00", "lieu": {"lieuRef": "AN", "libelleLong": "Assembl\u00e9e nationale"}, "cycleDeVie": {"etat": "Supprim\u00e9", "chrono": {"creation": "2025-12-08T00:00:00.000+01:00", "cloture": "2025-12-19T00:00:00.000+01:00"}}, "demandeur": null, "organeReuniRef": "PO838901", "participants": null, "visioConference": "false", "sessionRef": "SCR5A2026O1", "ouverturePresse": "true", "captationVideo": "true", "ODJ": {"convocationODJ": null, "resumeODJ": null, "pointsODJ": {"pointODJ": [{"@xsi:type": "podjSeanceConfPres_type", "uid": "RUANR5L17S2026IDS30110PT51315", "cycleDeVie": {"etat": "Supprim\u00e9", "chrono": {"creation": "2025-12-08T00:00:00.000+01:00", "cloture": "2025-12-19T00:00:00.000+01:00"}}, "objet": "Questions au Gouvernement", "demandeurPoint": null, "procedure": null, "dossiersLegislatifsRefs": null, "typePointODJ": "Questions au Gouvernement", "comiteSecret": "false", "textesAssocies": null, "natureTravauxODJ": "ODJPR"}, {"@xsi:type": "podjSeanceConfPres_type", "uid": "RUANR5L17S2026IDS30110PT51314", "cycleDeVie": {"etat": "Supprim\u00e9", "chrono": {"creation": "2025-12-08T00:00:00.000+01:00", "cloture": "2025-12-19T00:00:00.000+01:00"}}, "objet": "Sous r\u00e9serve de leur d\u00e9p\u00f4t, lecture des conclusions de la CMP sur le PLF pour 2026", "demandeurPoint": null, "procedure": null, "dossiersLegislatifsRefs": null, "typePointODJ": "Discussion", "comiteSecret": "false", "textesAssocies": null, "natureTravauxODJ": "ODJPR"}]}}, "compteRenduRef": null, "identifiants": {"numSeanceJO": null, "idJO": null, "quantieme": "Unique", "DateSeance": "2025-12-23+01:00"}}}