{"reunion": {"@xmlns": "http://schemas.assemblee-nationale.fr/referentiel", "@xmlns:xsi": "http://www.w3.org/2001/XMLSchema-instance", "@xsi:type": "reunionCommission_type", "uid": "RUANR5L17S2026IDC459862", "timeStampDebut": "2026-04-22T14:05:00.000+02:00", "timeStampFin": "2026-04-22T15:50:00.000+02:00", "lieu": {"lieuRef": "SLANPBS6350", "libelleLong": "Salle 6350 \u2013 Palais Bourbon, 1er \u00e9tage"}, "cycleDeVie": {"etat": "Confirm\u00e9", "chrono": {"creation": "2026-04-15T00:00:00.000+02:00", "cloture": null}}, "demandeur": null, "organeReuniRef": "PO59048", "participants": {"participantsInternes": {"participantInterne": [{"acteurRef": "PA793432", "presence": "pr\u00e9sent"}, {"acteurRef": "PA793780", "presence": "absent"}, {"acteurRef": "PA643143", "presence": "excus\u00e9"}, {"acteurRef": "PA267763", "presence": "absent"}, {"acteurRef": "PA606793", "presence": "absent"}, {"acteurRef": "PA795454", "presence": "excus\u00e9"}, {"acteurRef": "PA841531", "presence": "absent"}, {"acteurRef": "PA795616", "presence": "absent"}, {"acteurRef": "PA841885", "presence": "absent"}, {"acteurRef": "PA841487", "presence": "absent"}, {"acteurRef": "PA794094", "presence": "absent"}, {"acteurRef": "PA721908", "presence": "excus\u00e9"}, {"acteurRef": "PA793624", "presence": "pr\u00e9sent"}, {"acteurRef": "PA840075", "presence": "absent"}, {"acteurRef": "PA719472", "presence": "absent"}, {"acteurRef": "PA795864", "presence": "absent"}, {"acteurRef": "PA330240", "presence": "excus\u00e9"}, {"acteurRef": "PA721202", "presence": "pr\u00e9sent"}, {"acteurRef": "PA942", "presence": "pr\u00e9sent"}, {"acteurRef": "PA332523", "presence": "absent"}, {"acteurRef": "PA793166", "presence": "absent"}, {"acteurRef": "PA793928", "presence": "pr\u00e9sent"}, {"acteurRef": "PA722382", "presence": "pr\u00e9sent"}, {"acteurRef": "PA840135", "presence": "absent"}, {"acteurRef": "PA841251", "presence": "absent"}, {"acteurRef": "PA795884", "presence": "absent"}, {"acteurRef": "PA840801", "presence": "absent"}, {"acteurRef": "PA793892", "presence": "absent"}, {"acteurRef": "PA794470", "presence": "absent"}, {"acteurRef": "PA841605", "presence": "absent"}, {"acteurRef": "PA720560", "presence": "absent"}, {"acteurRef": "PA722070", "presence": "pr\u00e9sent"}, {"acteurRef": "PA719778", "presence": "absent"}, {"acteurRef": "PA346782", "presence": "pr\u00e9sent"}, {"acteurRef": "PA719798", "presence": "pr\u00e9sent"}, {"acteurRef": "PA841223", "presence": "absent"}, {"acteurRef": "PA841515", "presence": "pr\u00e9sent"}, {"acteurRef": "PA840979", "presence": "absent"}, {"acteurRef": "PA795298", "presence": "absent"}, {"acteurRef": "PA842029", "presence": "absent"}, {"acteurRef": "PA794750", "presence": "absent"}, {"acteurRef": "PA795974", "presence": "absent"}, {"acteurRef": "PA794114", "presence": "absent"}, {"acteurRef": "PA841563", "presence": "absent"}, {"acteurRef": "PA720146", "presence": "absent"}, {"acteurRef": "PA720728", "presence": "pr\u00e9sent"}, {"acteurRef": "PA795422", "presence": "absent"}, {"acteurRef": "PA842271", "presence": "absent"}, {"acteurRef": "PA793616", "presence": "pr\u00e9sent"}, {"acteurRef": "PA794686", "presence": "absent"}, {"acteurRef": "PA841931", "presence": "absent"}, {"acteurRef": "PA841463", "presence": "absent"}, {"acteurRef": "PA719640", "presence": "absent"}, {"acteurRef": "PA795176", "presence": "excus\u00e9"}, {"acteurRef": "PA795664", "presence": "absent"}, {"acteurRef": "PA841107", "presence": "absent"}, {"acteurRef": "PA795124", "presence": "pr\u00e9sent"}, {"acteurRef": "PA841381", "presence": "absent"}, {"acteurRef": "PA608172", "presence": "excus\u00e9"}, {"acteurRef": "PA793572", "presence": "excus\u00e9"}, {"acteurRef": "PA793094", "presence": "excus\u00e9"}, {"acteurRef": "PA841955", "presence": "pr\u00e9sent"}, {"acteurRef": "PA795528", "presence": "excus\u00e9"}, {"acteurRef": "PA842097", "presence": "pr\u00e9sent"}, {"acteurRef": "PA794954", "presence": "pr\u00e9sent"}, {"acteurRef": "PA605745", "presence": "excus\u00e9"}, {"acteurRef": "PA610002", "presence": "absent"}, {"acteurRef": "PA794802", "presence": "excus\u00e9"}, {"acteurRef": "PA795778", "presence": "pr\u00e9sent"}, {"acteurRef": "PA842299", "presence": "excus\u00e9"}, {"acteurRef": "PA842121", "presence": "excus\u00e9"}, {"acteurRef": "PA840809", "presence": "absent"}]}, "personnesAuditionnees": null}, "visioConference": "true", "sessionRef": null, "ouverturePresse": "true", "captationVideo": "true", "ODJ": {"convocationODJ": {"item": ["-  Nomination d\u2019un rapporteur sur la proposition de loi n\u00b0 1706", "-  Audition de Mme Carine CAMBY, pr\u00e9sidente de la 1\u00e8re chambre de la Cour des comptes, sur le rapport sur le budget de l\u2019\u00c9tat en 2025, sur le rapport de certification des comptes de l\u2019\u00c9tat pour 2025 et sur les avis du Haut Conseil des finances publiques relatifs au projet de loi relatif aux r\u00e9sultats de la gestion et portant approbation des comptes de l\u2019ann\u00e9e 2025 et au rapport annuel d\u2019avancement du plan budg\u00e9taire et structurel \u00e0 moyen terme"]}, "resumeODJ": {"item": ["nomination d\u2019un rapporteur sur la proposition de loi n\u00b0 1706 ;", "audition de Mme Carine Camby, pr\u00e9sidente de la 1\u00e8re chambre de la Cour des comptes, sur le rapport sur le budget de l\u2019\u00c9tat en 2025, sur le rapport de certification des comptes de l\u2019\u00c9tat pour 2025 et sur les avis du Haut Conseil des finances publiques relatifs au projet de loi relatif aux r\u00e9sultats de la gestion et portant approbation des comptes de l\u2019ann\u00e9e 2025 et au rapport annuel d\u2019avancement du plan budg\u00e9taire et structurel \u00e0 moyen terme."]}, "pointsODJ": {"pointODJ": [{"@xsi:type": "podjReunion_type", "uid": "RUANR5L17S2026IDC459862PT37279", "cycleDeVie": {"etat": "Confirm\u00e9", "chrono": {"creation": "2026-04-15T00:00:00.000+02:00", "cloture": null}}, "objet": "Nomination rapporteur", "demandeurPoint": null, "procedure": null, "dossiersLegislatifsRefs": {"dossierRef": "DLR5L17N52498"}, "typePointODJ": "Nomination rapporteur", "comiteSecret": "false", "textesAssocies": null}, {"@xsi:type": "podjReunion_type", "uid": "RUANR5L17S2026IDC459862PT37280", "cycleDeVie": {"etat": "Confirm\u00e9", "chrono": {"creation": "2026-04-15T00:00:00.000+02:00", "cloture": null}}, "objet": "Examen du texte", "demandeurPoint": null, "procedure": null, "dossiersLegislatifsRefs": {"dossierRef": "DLR5L17N53055"}, "typePointODJ": "Examen", "comiteSecret": "false", "textesAssocies": null}, {"@xsi:type": "podjReunion_type", "uid": "RUANR5L17S2026IDC459862PT37300", "cycleDeVie": {"etat": "Annul\u00e9", "chrono": {"creation": "2026-04-22T00:00:00.000+02:00", "cloture": "2026-04-22T00:00:00.000+02:00"}}, "objet": "Nomination d'un rapporteur", "demandeurPoint": null, "procedure": null, "dossiersLegislatifsRefs": null, "typePointODJ": "Nomination rapporteur", "comiteSecret": "false", "textesAssocies": null}]}}, "compteRenduRef": null, "formatReunion": "Ordinaire", "infosReunionsInternationale": {"estReunionInternationale": "false", "listePays": null}}}