{"reunion": {"@xmlns": "http://schemas.assemblee-nationale.fr/referentiel", "@xmlns:xsi": "http://www.w3.org/2001/XMLSchema-instance", "@xsi:type": "seance_type", "uid": "RUANR5L17S2025IDS28907", "timeStampDebut": "2025-01-14T15:00:00.000+01:00", "timeStampFin": "2025-01-14T20:05:00.000+01:00", "lieu": {"lieuRef": "AN", "libelleLong": "Assembl\u00e9e nationale"}, "cycleDeVie": {"etat": "Confirm\u00e9", "chrono": {"creation": "2024-12-16T00:00:00.000+01:00", "cloture": null}}, "demandeur": null, "organeReuniRef": "PO838901", "participants": null, "visioConference": "false", "sessionRef": "SCR5A2025O1", "ouverturePresse": "true", "captationVideo": "true", "ODJ": {"convocationODJ": null, "resumeODJ": null, "pointsODJ": {"pointODJ": [{"@xsi:type": "podjSeanceConfPres_type", "uid": "RUANR5L17S2025IDS28907PT48599", "cycleDeVie": {"etat": "Supprim\u00e9", "chrono": {"creation": "2024-12-16T00:00:00.000+01:00", "cloture": "2025-01-03T00:00:00.000+01:00"}}, "objet": "Questions au Gouvernement.", "demandeurPoint": null, "procedure": null, "dossiersLegislatifsRefs": null, "typePointODJ": "Questions au Gouvernement", "comiteSecret": "false", "textesAssocies": null, "natureTravauxODJ": "ODJPR"}, {"@xsi:type": "podjSeanceConfPres_type", "uid": "RUANR5L17S2025IDS28907PT48600", "cycleDeVie": {"etat": "Confirm\u00e9", "chrono": {"creation": "2024-12-16T00:00:00.000+01:00", "cloture": null}}, "objet": "D\u00e9claration du Gouvernement, suivie d'un d\u00e9bat (art. 50-1 de la Constitution)", "demandeurPoint": null, "procedure": null, "dossiersLegislatifsRefs": null, "typePointODJ": "D\u00e9claration du Gouvernement suivie d'un d\u00e9bat", "comiteSecret": "false", "textesAssocies": null, "natureTravauxODJ": "ODJPR", "dateConfPres": "2025-01-14+01:00"}]}}, "compteRenduRef": "CRSANR5L17S2025O1N066", "identifiants": {"numSeanceJO": "66", "idJO": "20250066", "quantieme": "Premi\u00e8re", "DateSeance": "2025-01-14+01:00"}}}