{"reunion": {"@xmlns": "http://schemas.assemblee-nationale.fr/referentiel", "@xmlns:xsi": "http://www.w3.org/2001/XMLSchema-instance", "@xsi:type": "reunionCommission_type", "uid": "RUANR5L17S2026IDC457602", "timeStampDebut": "2025-10-06T15:00:00.000+02:00", "timeStampFin": "2025-10-06T16:20:00.000+02:00", "lieu": {"lieuRef": "SLANPBS6237", "libelleLong": "Salle 6237 \u2013 Palais Bourbon, 2\u00e8me sous-sol"}, "cycleDeVie": {"etat": "Confirm\u00e9", "chrono": {"creation": "2025-10-03T00:00:00.000+02:00", "cloture": null}}, "demandeur": null, "organeReuniRef": "PO870844", "participants": {"participantsInternes": {"participantInterne": [{"acteurRef": "PA795762", "presence": "absent"}, {"acteurRef": "PA841047", "presence": "absent"}, {"acteurRef": "PA720468", "presence": "absent"}, {"acteurRef": "PA840235", "presence": "absent"}, {"acteurRef": "PA793832", "presence": "excus\u00e9"}, {"acteurRef": "PA266797", "presence": "absent"}, {"acteurRef": "PA721296", "presence": "absent"}, {"acteurRef": "PA795258", "presence": "pr\u00e9sent"}, {"acteurRef": "PA842013", "presence": "absent"}, {"acteurRef": "PA719404", "presence": "absent"}, {"acteurRef": "PA642988", "presence": "absent"}, {"acteurRef": "PA795176", "presence": "absent"}, {"acteurRef": "PA643157", "presence": "absent"}, {"acteurRef": "PA610654", "presence": "absent"}, {"acteurRef": "PA841191", "presence": "absent"}, {"acteurRef": "PA721234", "presence": "absent"}, {"acteurRef": "PA721062", "presence": "absent"}, {"acteurRef": "PA795876", "presence": "absent"}, {"acteurRef": "PA842227", "presence": "pr\u00e9sent"}, {"acteurRef": "PA721110", "presence": "absent"}, {"acteurRef": "PA757225", "presence": "absent"}, {"acteurRef": "PA720952", "presence": "absent"}, {"acteurRef": "PA794502", "presence": "absent"}, {"acteurRef": "PA841553", "presence": "absent"}, {"acteurRef": "PA720992", "presence": "absent"}]}, "personnesAuditionnees": null}, "visioConference": "true", "sessionRef": null, "ouverturePresse": "true", "captationVideo": "true", "ODJ": {"convocationODJ": {"item": "\u2013 Table ronde, ouverte \u00e0 la presse, r\u00e9unissant :\r- M. Richard Garcia-Bosch-de Morales - de Sola, pr\u00e9sident du tribunal sup\u00e9rieur d\u2019appel de Saint-Pierre-et-Miquelon\r- M. Yves Couroux, procureur de la R\u00e9publique pr\u00e8s le tribunal sup\u00e9rieur d\u2019appel de Saint-Pierre-et-Miquelon\r- Mme Nicole Peix, pr\u00e9sidente du tribunal de premi\u00e8re instance de Saint-Pierre-et-Miquelon"}, "resumeODJ": {"item": ["table ronde, ouverte \u00e0 la presse, r\u00e9unissant :", "M. Richard Garcia-Bosch-de Morales - de Sola, pr\u00e9sident du tribunal sup\u00e9rieur d\u2019appel de Saint-Pierre-et-Miquelon ;", "M. Yves Couroux, procureur de la R\u00e9publique pr\u00e8s le tribunal sup\u00e9rieur d\u2019appel de Saint-Pierre-et-Miquelon ;", "Mme Nicole Peix, pr\u00e9sidente du tribunal de premi\u00e8re instance de Saint-Pierre-et-Miquelon."]}, "pointsODJ": null}, "compteRenduRef": "CRCANR5L17S2026PO870844N036", "formatReunion": "Ordinaire", "infosReunionsInternationale": {"estReunionInternationale": "false", "listePays": null}}}