{"reunion": {"@xmlns": "http://schemas.assemblee-nationale.fr/referentiel", "@xmlns:xsi": "http://www.w3.org/2001/XMLSchema-instance", "@xsi:type": "reunionCommission_type", "uid": "RUANR5L17S2025IDC455079", "timeStampDebut": "2025-03-05T15:00:00.000+01:00", "timeStampFin": "2025-03-05T16:30:00.000+01:00", "lieu": {"lieuRef": null, "libelleLong": "Visioconf\u00e9rence sans salle"}, "cycleDeVie": {"etat": "Confirm\u00e9", "chrono": {"creation": "2025-02-28T00:00:00.000+01:00", "cloture": null}}, "demandeur": null, "organeReuniRef": "PO862556", "participants": {"participantsInternes": null, "personnesAuditionnees": null}, "visioConference": "true", "sessionRef": null, "ouverturePresse": "false", "captationVideo": "false", "ODJ": {"convocationODJ": {"item": "Table ronde \u00ab Approche historique et sociologique de la restauration des cours d\u2019eau \u00bb\rMme Marie Lusson, sociologue des sciences autrice de la th\u00e8se \u00ab Restaurer des rivi\u00e8res \u00e0 l\u2019\u00e8re de l\u2019Anthropoc\u00e8ne \u00bb, doctorante \u00e0 l\u2019Institut national de recherche pour l\u2019agriculture, l\u2019alimentation et l\u2019environnement (Inrae)\rMme Christelle Gramaglia, sociologue des sciences de l\u2019environnement \u00e0 l\u2019Inrae et \u00e0 l\u2019universit\u00e9 de Montpellier"}, "resumeODJ": {"item": "Table ronde \u00ab Approche historique et sociologique de la restauration des cours d\u2019eau \u00bb\rMme Marie Lusson, sociologue des sciences autrice de la th\u00e8se \u00ab Restaurer des rivi\u00e8res \u00e0 l\u2019\u00e8re de l\u2019Anthropoc\u00e8ne \u00bb, doctorante \u00e0 l\u2019Institut national de recherche pour l\u2019agriculture, l\u2019alimentation et l\u2019environnement (Inrae)\rMme Christelle Gramaglia, sociologue des sciences de l\u2019environnement \u00e0 l\u2019Inrae et \u00e0 l\u2019universit\u00e9 de Montpellier"}, "pointsODJ": null}, "compteRenduRef": null, "formatReunion": "Ordinaire", "infosReunionsInternationale": {"estReunionInternationale": "false", "listePays": null}}}