{"reunion": {"@xmlns": "http://schemas.assemblee-nationale.fr/referentiel", "@xmlns:xsi": "http://www.w3.org/2001/XMLSchema-instance", "@xsi:type": "reunionCommission_type", "uid": "RUANR5L17S2025IDC455093", "timeStampDebut": "2025-03-05T16:30:00.000+01:00", "lieu": {"lieuRef": "SLAN101RUSGABR", "libelleLong": "Salon Gabriel \u2013 101 rue de l'Universit\u00e9, Rez-de-chauss\u00e9e"}, "cycleDeVie": {"etat": "Confirm\u00e9", "chrono": {"creation": "2025-03-03T00:00:00.000+01:00", "cloture": null}}, "demandeur": null, "organeReuniRef": "PO854718", "participants": {"participantsInternes": null, "personnesAuditionnees": {"personneAuditionnee": [null, null, null]}}, "visioConference": "false", "sessionRef": null, "ouverturePresse": "false", "captationVideo": "false", "ODJ": {"convocationODJ": {"item": "Audition de M. Christophe Peyrel, haut fonctionnaire de d\u00e9fense et de s\u00e9curit\u00e9 adjoint, chef du service de d\u00e9fense et de s\u00e9curit\u00e9 des minist\u00e8res de l\u2019\u00e9ducation, de la jeunesse, des sports, de l\u2019enseignement sup\u00e9rieur et de la recherche, accompagn\u00e9 de Mme Catherine Billard, sous-directrice de la protection de la recherche et des activit\u00e9s critiques, et de M. J\u00e9r\u00e9mie Castello, adjoint au chef du bureau de la protection du potentiel scientifique et technique et de l\u2019intelligence \u00e9conomique."}, "resumeODJ": {"item": "audition de M. Christophe Peyrel, haut fonctionnaire de d\u00e9fense et de s\u00e9curit\u00e9 adjoint, chef du service de d\u00e9fense et de s\u00e9curit\u00e9 des minist\u00e8res de l\u2019\u00e9ducation, de la jeunesse, des sports, de l\u2019enseignement sup\u00e9rieur et de la recherche, accompagn\u00e9 de Mme Catherine Billard, sous-directrice de la protection de la recherche et des activit\u00e9s critiques, et de M. J\u00e9r\u00e9mie Castello, adjoint au chef du bureau de la protection du potentiel scientifique et technique et de l\u2019intelligence \u00e9conomique."}, "pointsODJ": null}, "compteRenduRef": null, "formatReunion": "Ordinaire", "infosReunionsInternationale": {"estReunionInternationale": "false", "listePays": null}}}