{"reunion": {"@xmlns": "http://schemas.assemblee-nationale.fr/referentiel", "@xmlns:xsi": "http://www.w3.org/2001/XMLSchema-instance", "@xsi:type": "reunionInitParlementaire_type", "uid": "RUANR5L17S2026IDFL458762", "timeStampDebut": "2026-02-17T14:00:00.000+01:00", "lieu": {"lieuRef": null, "libelleLong": "salon Mansart (32 rue Saint-Dominique)"}, "cycleDeVie": {"etat": "Confirm\u00e9", "chrono": {"creation": "2026-01-16T00:00:00.000+01:00", "cloture": null}}, "demandeur": null, "organeReuniRef": "PO854354", "participants": null, "visioConference": "false", "typeReunion": "GE", "ODJ": {"convocationODJ": {"item": "Audition du groupe SACPA sur le th\u00e8me de l\u2019abandon des animaux et le d\u00e9lai en fourri\u00e8re."}, "resumeODJ": null}}}