{"reunion": {"@xmlns": "http://schemas.assemblee-nationale.fr/referentiel", "@xmlns:xsi": "http://www.w3.org/2001/XMLSchema-instance", "@xsi:type": "reunionCommission_type", "uid": "RUANR5L17S2026IDC459681", "timeStampDebut": "2026-04-08T11:00:00.000+02:00", "timeStampFin": "2026-04-08T12:50:00.000+02:00", "lieu": {"lieuRef": "SLAN101RUSLAM", "libelleLong": "Salle Lamartine \u2013 101 rue de l'Universit\u00e9, 1er sous-sol"}, "cycleDeVie": {"etat": "Confirm\u00e9", "chrono": {"creation": "2026-04-03T00:00:00.000+02:00", "cloture": null}}, "demandeur": null, "organeReuniRef": "PO59048", "participants": {"participantsInternes": {"participantInterne": [{"acteurRef": "PA793432", "presence": "absent"}, {"acteurRef": "PA793780", "presence": "absent"}, {"acteurRef": "PA643143", "presence": "excus\u00e9"}, {"acteurRef": "PA267763", "presence": "absent"}, {"acteurRef": "PA606793", "presence": "absent"}, {"acteurRef": "PA795454", "presence": "excus\u00e9"}, {"acteurRef": "PA795616", "presence": "pr\u00e9sent"}, {"acteurRef": "PA720162", "presence": "absent"}, {"acteurRef": "PA841885", "presence": "absent"}, {"acteurRef": "PA841487", "presence": "pr\u00e9sent"}, {"acteurRef": "PA794094", "presence": "pr\u00e9sent"}, {"acteurRef": "PA342240", "presence": "pr\u00e9sent"}, {"acteurRef": "PA721908", "presence": "excus\u00e9"}, {"acteurRef": "PA793624", "presence": "absent"}, {"acteurRef": "PA719138", "presence": "pr\u00e9sent"}, {"acteurRef": "PA840075", "presence": "pr\u00e9sent"}, {"acteurRef": "PA795864", "presence": "pr\u00e9sent"}, {"acteurRef": "PA330240", "presence": "excus\u00e9"}, {"acteurRef": "PA721202", "presence": "pr\u00e9sent"}, {"acteurRef": "PA942", "presence": "pr\u00e9sent"}, {"acteurRef": "PA332523", "presence": "pr\u00e9sent"}, {"acteurRef": "PA793166", "presence": "pr\u00e9sent"}, {"acteurRef": "PA793928", "presence": "pr\u00e9sent"}, {"acteurRef": "PA722382", "presence": "pr\u00e9sent"}, {"acteurRef": "PA840135", "presence": "pr\u00e9sent"}, {"acteurRef": "PA841251", "presence": "pr\u00e9sent"}, {"acteurRef": "PA795884", "presence": "excus\u00e9"}, {"acteurRef": "PA840801", "presence": "pr\u00e9sent"}, {"acteurRef": "PA793892", "presence": "pr\u00e9sent"}, {"acteurRef": "PA794470", "presence": "pr\u00e9sent"}, {"acteurRef": "PA841605", "presence": "pr\u00e9sent"}, {"acteurRef": "PA720560", "presence": "pr\u00e9sent"}, {"acteurRef": "PA721764", "presence": "absent"}, {"acteurRef": "PA719778", "presence": "pr\u00e9sent"}, {"acteurRef": "PA346782", "presence": "pr\u00e9sent"}, {"acteurRef": "PA719798", "presence": "pr\u00e9sent"}, {"acteurRef": "PA841223", "presence": "pr\u00e9sent"}, {"acteurRef": "PA841515", "presence": "pr\u00e9sent"}, {"acteurRef": "PA712014", "presence": "absent"}, {"acteurRef": "PA840979", "presence": "absent"}, {"acteurRef": "PA795298", "presence": "absent"}, {"acteurRef": "PA842029", "presence": "pr\u00e9sent"}, {"acteurRef": "PA795974", "presence": "pr\u00e9sent"}, {"acteurRef": "PA608016", "presence": "absent"}, {"acteurRef": "PA841563", "presence": "pr\u00e9sent"}, {"acteurRef": "PA794518", "presence": "absent"}, {"acteurRef": "PA720728", "presence": "pr\u00e9sent"}, {"acteurRef": "PA795422", "presence": "excus\u00e9"}, {"acteurRef": "PA842271", "presence": "pr\u00e9sent"}, {"acteurRef": "PA793616", "presence": "pr\u00e9sent"}, {"acteurRef": "PA794686", "presence": "absent"}, {"acteurRef": "PA841463", "presence": "absent"}, {"acteurRef": "PA719640", "presence": "absent"}, {"acteurRef": "PA795176", "presence": "excus\u00e9"}, {"acteurRef": "PA795664", "presence": "absent"}, {"acteurRef": "PA841107", "presence": "pr\u00e9sent"}, {"acteurRef": "PA795124", "presence": "pr\u00e9sent"}, {"acteurRef": "PA841381", "presence": "absent"}, {"acteurRef": "PA608172", "presence": "excus\u00e9"}, {"acteurRef": "PA793572", "presence": "excus\u00e9"}, {"acteurRef": "PA793094", "presence": "pr\u00e9sent"}, {"acteurRef": "PA841955", "presence": "pr\u00e9sent"}, {"acteurRef": "PA795528", "presence": "excus\u00e9"}, {"acteurRef": "PA842097", "presence": "pr\u00e9sent"}, {"acteurRef": "PA794954", "presence": "pr\u00e9sent"}, {"acteurRef": "PA605745", "presence": "excus\u00e9"}, {"acteurRef": "PA610002", "presence": "pr\u00e9sent"}, {"acteurRef": "PA794802", "presence": "pr\u00e9sent"}, {"acteurRef": "PA795778", "presence": "pr\u00e9sent"}, {"acteurRef": "PA842299", "presence": "excus\u00e9"}, {"acteurRef": "PA840809", "presence": "absent"}]}, "personnesAuditionnees": null}, "visioConference": "false", "sessionRef": null, "ouverturePresse": "true", "captationVideo": "true", "ODJ": {"convocationODJ": {"item": "\u2013 Audition, conjointe avec la commission des affaires \u00e9conomiques, de M. Fran\u00e7ois BOUSSAGOL, pr\u00e9sident-directeur g\u00e9n\u00e9ral de la Soci\u00e9t\u00e9 anonyme de gestion de stocks de s\u00e9curit\u00e9 (SAGESS), et M. Son LENGOC, secr\u00e9taire g\u00e9n\u00e9ral et directeur finances"}, "resumeODJ": {"item": "audition, conjointe avec la commission des affaires \u00e9conomiques, de M. Fran\u00e7ois Boussagol, pr\u00e9sident-directeur g\u00e9n\u00e9ral de la Soci\u00e9t\u00e9 anonyme de gestion de stocks de s\u00e9curit\u00e9 (SAGESS), et M. Son Lengoc, secr\u00e9taire g\u00e9n\u00e9ral et directeur finances."}, "pointsODJ": null}, "compteRenduRef": "CRCANR5L17S2026PO59048N078", "formatReunion": "Ordinaire", "infosReunionsInternationale": {"estReunionInternationale": "false", "listePays": null}}}