{"reunion": {"@xmlns": "http://schemas.assemblee-nationale.fr/referentiel", "@xmlns:xsi": "http://www.w3.org/2001/XMLSchema-instance", "@xsi:type": "reunionCommission_type", "uid": "RUANR5L17S2025IDC457363", "timeStampDebut": "2025-09-17T11:30:00.000+02:00", "timeStampFin": "2025-09-17T12:40:00.000+02:00", "lieu": {"lieuRef": "SLANPBS6241", "libelleLong": "Salle 6241 \u2013 Palais Bourbon, 2\u00e8me sous-sol"}, "cycleDeVie": {"etat": "Confirm\u00e9", "chrono": {"creation": "2025-09-02T00:00:00.000+02:00", "cloture": null}}, "demandeur": null, "organeReuniRef": "PO419610", "participants": {"participantsInternes": {"participantInterne": [{"acteurRef": "PA793262", "presence": "pr\u00e9sent"}, {"acteurRef": "PA793992", "presence": "absent"}, {"acteurRef": "PA841067", "presence": "excus\u00e9"}, {"acteurRef": "PA841207", "presence": "excus\u00e9"}, {"acteurRef": "PA794906", "presence": "pr\u00e9sent"}, {"acteurRef": "PA841495", "presence": "absent"}, {"acteurRef": "PA795144", "presence": "absent"}, {"acteurRef": "PA793238", "presence": "absent"}, {"acteurRef": "PA335999", "presence": "pr\u00e9sent"}, {"acteurRef": "PA342415", "presence": "pr\u00e9sent"}, {"acteurRef": "PA841315", "presence": "pr\u00e9sent"}, {"acteurRef": "PA332228", "presence": "absent"}, {"acteurRef": "PA840997", "presence": "pr\u00e9sent"}, {"acteurRef": "PA720162", "presence": "absent"}, {"acteurRef": "PA342240", "presence": "excus\u00e9"}, {"acteurRef": "PA794710", "presence": "pr\u00e9sent"}, {"acteurRef": "PA722000", "presence": "absent"}, {"acteurRef": "PA794798", "presence": "absent"}, {"acteurRef": "PA793736", "presence": "pr\u00e9sent"}, {"acteurRef": "PA795430", "presence": "pr\u00e9sent"}, {"acteurRef": "PA720386", "presence": "pr\u00e9sent"}, {"acteurRef": "PA712015", "presence": "absent"}, {"acteurRef": "PA794854", "presence": "pr\u00e9sent"}, {"acteurRef": "PA793246", "presence": "absent"}, {"acteurRef": "PA793980", "presence": "absent"}, {"acteurRef": "PA722366", "presence": "pr\u00e9sent"}, {"acteurRef": "PA841139", "presence": "absent"}, {"acteurRef": "PA841605", "presence": "absent"}, {"acteurRef": "PA793592", "presence": "absent"}, {"acteurRef": "PA721764", "presence": "absent"}, {"acteurRef": "PA841017", "presence": "absent"}, {"acteurRef": "PA794146", "presence": "pr\u00e9sent"}, {"acteurRef": "PA795516", "presence": "pr\u00e9sent"}, {"acteurRef": "PA842125", "presence": "pr\u00e9sent"}, {"acteurRef": "PA794354", "presence": "pr\u00e9sent"}, {"acteurRef": "PA719388", "presence": "absent"}, {"acteurRef": "PA720342", "presence": "absent"}, {"acteurRef": "PA721852", "presence": "pr\u00e9sent"}, {"acteurRef": "PA841837", "presence": "pr\u00e9sent"}, {"acteurRef": "PA795374", "presence": "pr\u00e9sent"}, {"acteurRef": "PA695512", "presence": "pr\u00e9sent"}, {"acteurRef": "PA642988", "presence": "absent"}, {"acteurRef": "PA774958", "presence": "absent"}, {"acteurRef": "PA840967", "presence": "pr\u00e9sent"}, {"acteurRef": "PA794590", "presence": "absent"}, {"acteurRef": "PA795730", "presence": "absent"}, {"acteurRef": "PA719080", "presence": "pr\u00e9sent"}, {"acteurRef": "PA795100", "presence": "pr\u00e9sent"}, {"acteurRef": "PA841825", "presence": "absent"}, {"acteurRef": "PA719436", "presence": "absent"}, {"acteurRef": "PA795482", "presence": "pr\u00e9sent"}, {"acteurRef": "PA795664", "presence": "pr\u00e9sent"}, {"acteurRef": "PA794810", "presence": "pr\u00e9sent"}, {"acteurRef": "PA721486", "presence": "absent"}, {"acteurRef": "PA841191", "presence": "pr\u00e9sent"}, {"acteurRef": "PA720644", "presence": "absent"}, {"acteurRef": "PA721270", "presence": "absent"}, {"acteurRef": "PA817211", "presence": "pr\u00e9sent"}, {"acteurRef": "PA607553", "presence": "pr\u00e9sent"}, {"acteurRef": "PA795270", "presence": "absent"}, {"acteurRef": "PA720092", "presence": "pr\u00e9sent"}, {"acteurRef": "PA842227", "presence": "pr\u00e9sent"}, {"acteurRef": "PA266808", "presence": "excus\u00e9"}, {"acteurRef": "PA841327", "presence": "absent"}, {"acteurRef": "PA793796", "presence": "pr\u00e9sent"}, {"acteurRef": "PA794166", "presence": "pr\u00e9sent"}, {"acteurRef": "PA841713", "presence": "pr\u00e9sent"}, {"acteurRef": "PA793816", "presence": "pr\u00e9sent"}, {"acteurRef": "PA793298", "presence": "pr\u00e9sent"}, {"acteurRef": "PA607395", "presence": "pr\u00e9sent"}, {"acteurRef": "PA795164", "presence": "pr\u00e9sent"}, {"acteurRef": "PA607090", "presence": "absent"}, {"acteurRef": "PA841479", "presence": "absent"}]}, "personnesAuditionnees": null}, "visioConference": "false", "sessionRef": null, "ouverturePresse": "true", "captationVideo": "true", "ODJ": {"convocationODJ": {"item": "\u2013 Pr\u00e9sentation, en application de l\u2019article 148 alin\u00e9a 3 du R\u00e8glement, de deux p\u00e9titions renvoy\u00e9es \u00e0 la commission, intitul\u00e9es \u00ab Non \u00e0 la Loi Duplomb - Pour la sant\u00e9, la s\u00e9curit\u00e9, l\u2019intelligence collective \u00bb (n\u00b0 3014) et \u00ab P\u00e9tition contre la loi Duplomb \u00bb (n\u00b0 3092) (Mme H\u00e9l\u00e8ne Laporte, rapporteure), et vote en vue de leur classement ou de leur examen par la commission."}, "resumeODJ": {"item": "pr\u00e9sentation, en application de l\u2019article 148 alin\u00e9a 3 du R\u00e8glement, de deux p\u00e9titions renvoy\u00e9es \u00e0 la commission, intitul\u00e9es \u00ab Non \u00e0 la Loi Duplomb - Pour la sant\u00e9, la s\u00e9curit\u00e9, l\u2019intelligence collective \u00bb (n\u00b0 3014) et \u00ab P\u00e9tition contre la loi Duplomb \u00bb (n\u00b0 3092) (Mme H\u00e9l\u00e8ne Laporte, rapporteure), et vote en vue de leur classement ou de leur examen par la commission."}, "pointsODJ": null}, "compteRenduRef": "CRCANR5L17S2025PO419610N126", "formatReunion": "Ordinaire", "infosReunionsInternationale": {"estReunionInternationale": "false", "listePays": null}}}